{
    "asset": {
        "format": "jpg",
        "id": "fe883e2e44ae75483ea329a0916ba1d8",
        "name": "00008.jpg",
        "path": "file:C:/Users/Bhadr/Desktop/Car-Body-Parts-Challenge/TrainYourOwnYOLO/Data/Source_Images/Training/00008.jpg",
        "size": {
            "width": 639,
            "height": 480
        },
        "state": 2,
        "type": 1
    },
    "regions": [
        {
            "id": "bi-RWgwu6",
            "type": "RECTANGLE",
            "tags": [
                "Light"
            ],
            "boundingBox": {
                "height": 71.0508598715572,
                "width": 129.69937133789062,
                "left": 315.8114840756556,
                "top": 199.59321620100636
            },
            "points": [
                {
                    "x": 315.8114840756556,
                    "y": 199.59321620100636
                },
                {
                    "x": 445.5108554135462,
                    "y": 199.59321620100636
                },
                {
                    "x": 445.5108554135462,
                    "y": 270.64407607256356
                },
                {
                    "x": 315.8114840756556,
                    "y": 270.64407607256356
                }
            ]
        },
        {
            "id": "OI84Z10jI",
            "type": "RECTANGLE",
            "tags": [
                "Light"
            ],
            "boundingBox": {
                "height": 52.610152939618644,
                "width": 66.20635286562002,
                "left": 524.741461784217,
                "top": 184.94916495630295
            },
            "points": [
                {
                    "x": 524.741461784217,
                    "y": 184.94916495630295
                },
                {
                    "x": 590.947814649837,
                    "y": 184.94916495630295
                },
                {
                    "x": 590.947814649837,
                    "y": 237.5593178959216
                },
                {
                    "x": 524.741461784217,
                    "y": 237.5593178959216
                }
            ]
        },
        {
            "id": "2jq9VkJ7h",
            "type": "RECTANGLE",
            "tags": [
                "Glass"
            ],
            "boundingBox": {
                "height": 86.23729641154661,
                "width": 276.2216643315212,
                "left": 219.2153305734039,
                "top": 79.72881769729872
            },
            "points": [
                {
                    "x": 219.2153305734039,
                    "y": 79.72881769729872
                },
                {
                    "x": 495.4369949049251,
                    "y": 79.72881769729872
                },
                {
                    "x": 495.4369949049251,
                    "y": 165.96611410884532
                },
                {
                    "x": 219.2153305734039,
                    "y": 165.96611410884532
                }
            ]
        },
        {
            "id": "2Ged7K-d9",
            "type": "RECTANGLE",
            "tags": [
                "Wheel"
            ],
            "boundingBox": {
                "height": 156.20338569253178,
                "width": 96.59619490508061,
                "left": 163.31977261099846,
                "top": 231.59322447695973
            },
            "points": [
                {
                    "x": 163.31977261099846,
                    "y": 231.59322447695973
                },
                {
                    "x": 259.91596751607904,
                    "y": 231.59322447695973
                },
                {
                    "x": 259.91596751607904,
                    "y": 387.7966101694915
                },
                {
                    "x": 163.31977261099846,
                    "y": 387.7966101694915
                }
            ]
        },
        {
            "id": "e-V3DNz6T",
            "type": "RECTANGLE",
            "tags": [
                "Wheel"
            ],
            "boundingBox": {
                "height": 82.44068210407839,
                "width": 34.731197770234125,
                "left": 68.89430732484077,
                "top": 159.45763539459745
            },
            "points": [
                {
                    "x": 68.89430732484077,
                    "y": 159.45763539459745
                },
                {
                    "x": 103.62550509507489,
                    "y": 159.45763539459745
                },
                {
                    "x": 103.62550509507489,
                    "y": 241.89831749867582
                },
                {
                    "x": 68.89430732484077,
                    "y": 241.89831749867582
                }
            ]
        },
        {
            "id": "-_-l1O3za",
            "type": "RECTANGLE",
            "tags": [
                "SideGlass"
            ],
            "boundingBox": {
                "height": 27.11864406779661,
                "width": 37.98726114649681,
                "left": 78.11976847071556,
                "top": 119.32203389830508
            },
            "points": [
                {
                    "x": 78.11976847071556,
                    "y": 119.32203389830508
                },
                {
                    "x": 116.10702961721238,
                    "y": 119.32203389830508
                },
                {
                    "x": 116.10702961721238,
                    "y": 146.4406779661017
                },
                {
                    "x": 78.11976847071556,
                    "y": 146.4406779661017
                }
            ]
        },
        {
            "id": "qrtoM6_DT",
            "type": "RECTANGLE",
            "tags": [
                "Door"
            ],
            "boundingBox": {
                "height": 182.2373005495233,
                "width": 66.20637356703448,
                "left": 106.88156847133757,
                "top": 92.20338983050847
            },
            "points": [
                {
                    "x": 106.88156847133757,
                    "y": 92.20338983050847
                },
                {
                    "x": 173.08794203837206,
                    "y": 92.20338983050847
                },
                {
                    "x": 173.08794203837206,
                    "y": 274.44069038003175
                },
                {
                    "x": 106.88156847133757,
                    "y": 274.44069038003175
                }
            ]
        },
        {
            "id": "TUGIc-nZ9",
            "type": "RECTANGLE",
            "tags": [
                "Wheel"
            ],
            "boundingBox": {
                "height": 94.37291032176907,
                "width": 38.82672420428816,
                "left": 600.1732757957118,
                "top": 202.305080607786
            },
            "points": [
                {
                    "x": 600.1732757957118,
                    "y": 202.305080607786
                },
                {
                    "x": 639,
                    "y": 202.305080607786
                },
                {
                    "x": 639,
                    "y": 296.67799092955505
                },
                {
                    "x": 600.1732757957118,
                    "y": 296.67799092955505
                }
            ]
        },
        {
            "id": "G85WXJRb5",
            "type": "RECTANGLE",
            "tags": [
                "Light"
            ],
            "boundingBox": {
                "height": 28.203373278601692,
                "width": 28.219112420537666,
                "left": 5.401309553984624,
                "top": 130.71187682070973
            },
            "points": [
                {
                    "x": 5.401309553984624,
                    "y": 130.71187682070973
                },
                {
                    "x": 33.620421974522294,
                    "y": 130.71187682070973
                },
                {
                    "x": 33.620421974522294,
                    "y": 158.91525009931144
                },
                {
                    "x": 5.401309553984624,
                    "y": 158.91525009931144
                }
            ]
        }
    ],
    "version": "2.1.0"
}