{
    "asset": {
        "format": "jpg",
        "id": "8d942067442c9f41172d35cc0dea6ef6",
        "name": "00040.jpg",
        "path": "file:C:/Users/Bhadr/Desktop/Car-Body-Parts-Challenge/TrainYourOwnYOLO/Data/Source_Images/Training/00040.jpg",
        "size": {
            "width": 750,
            "height": 469
        },
        "state": 2,
        "type": 1
    },
    "regions": [
        {
            "id": "F3DztDzZb",
            "type": "RECTANGLE",
            "tags": [
                "SideGlass"
            ],
            "boundingBox": {
                "height": 41.06388523267663,
                "width": 45.548300488372774,
                "left": 272.58668307846915,
                "top": 161.74171235000176
            },
            "points": [
                {
                    "x": 272.58668307846915,
                    "y": 161.74171235000176
                },
                {
                    "x": 318.1349835668419,
                    "y": 161.74171235000176
                },
                {
                    "x": 318.1349835668419,
                    "y": 202.8055975826784
                },
                {
                    "x": 272.58668307846915,
                    "y": 202.8055975826784
                }
            ]
        },
        {
            "id": "0Bx2QvZDB",
            "type": "RECTANGLE",
            "tags": [
                "SideGlass"
            ],
            "boundingBox": {
                "height": 34.876166210717884,
                "width": 37.675752076682585,
                "left": 537.5819970428553,
                "top": 155.83526986506746
            },
            "points": [
                {
                    "x": 537.5819970428553,
                    "y": 155.83526986506746
                },
                {
                    "x": 575.2577491195378,
                    "y": 155.83526986506746
                },
                {
                    "x": 575.2577491195378,
                    "y": 190.71143607578534
                },
                {
                    "x": 537.5819970428553,
                    "y": 190.71143607578534
                }
            ]
        },
        {
            "id": "AfjABsOFz",
            "type": "RECTANGLE",
            "tags": [
                "Glass"
            ],
            "boundingBox": {
                "height": 65.25216532968867,
                "width": 230.55295220243676,
                "left": 317.57262497162753,
                "top": 124.05297389452247
            },
            "points": [
                {
                    "x": 317.57262497162753,
                    "y": 124.05297389452247
                },
                {
                    "x": 548.1255771740642,
                    "y": 124.05297389452247
                },
                {
                    "x": 548.1255771740642,
                    "y": 189.30513922421113
                },
                {
                    "x": 317.57262497162753,
                    "y": 189.30513922421113
                }
            ]
        },
        {
            "id": "UXLWwRj6g",
            "type": "RECTANGLE",
            "tags": [
                "Light"
            ],
            "boundingBox": {
                "height": 50.626686656671666,
                "width": 90.53419947959378,
                "left": 350.1874500049423,
                "top": 224.18130543492902
            },
            "points": [
                {
                    "x": 350.1874500049423,
                    "y": 224.18130543492902
                },
                {
                    "x": 440.7216494845361,
                    "y": 224.18130543492902
                },
                {
                    "x": 440.7216494845361,
                    "y": 274.8079920916007
                },
                {
                    "x": 350.1874500049423,
                    "y": 274.8079920916007
                }
            ]
        },
        {
            "id": "CWvdEH6bv",
            "type": "RECTANGLE",
            "tags": [
                "Light"
            ],
            "boundingBox": {
                "height": 43.87645747743804,
                "width": 40.4873305430676,
                "left": 615.0421743205249,
                "top": 220.2436699588438
            },
            "points": [
                {
                    "x": 615.0421743205249,
                    "y": 220.2436699588438
                },
                {
                    "x": 655.5295048635925,
                    "y": 220.2436699588438
                },
                {
                    "x": 655.5295048635925,
                    "y": 264.12012743628185
                },
                {
                    "x": 615.0421743205249,
                    "y": 264.12012743628185
                }
            ]
        },
        {
            "id": "v1ZQ2oLBZ",
            "type": "RECTANGLE",
            "tags": [
                "Wheel"
            ],
            "boundingBox": {
                "height": 131.06688373342627,
                "width": 73.6644712696594,
                "left": 305.90441345386455,
                "top": 267.0733594079425
            },
            "points": [
                {
                    "x": 305.90441345386455,
                    "y": 267.0733594079425
                },
                {
                    "x": 379.5688847235239,
                    "y": 267.0733594079425
                },
                {
                    "x": 379.5688847235239,
                    "y": 398.1402431413688
                },
                {
                    "x": 305.90441345386455,
                    "y": 398.1402431413688
                }
            ]
        },
        {
            "id": "KMUG3biJg",
            "type": "RECTANGLE",
            "tags": [
                "Wheel"
            ],
            "boundingBox": {
                "height": 103.50347831760389,
                "width": 46.6728889729894,
                "left": 218.88474068467377,
                "top": 246.11952344445453
            },
            "points": [
                {
                    "x": 218.88474068467377,
                    "y": 246.11952344445453
                },
                {
                    "x": 265.55762965766314,
                    "y": 246.11952344445453
                },
                {
                    "x": 265.55762965766314,
                    "y": 349.62300176205844
                },
                {
                    "x": 218.88474068467377,
                    "y": 349.62300176205844
                }
            ]
        },
        {
            "id": "Gold_nDIe",
            "type": "RECTANGLE",
            "tags": [
                "Door"
            ],
            "boundingBox": {
                "height": 207.00691371843376,
                "width": 51.73385891829458,
                "left": 260.77788191190257,
                "top": 128.55311952788256
            },
            "points": [
                {
                    "x": 260.77788191190257,
                    "y": 128.55311952788256
                },
                {
                    "x": 312.51174083019714,
                    "y": 128.55311952788256
                },
                {
                    "x": 312.51174083019714,
                    "y": 335.5600332463163
                },
                {
                    "x": 260.77788191190257,
                    "y": 335.5600332463163
                }
            ]
        }
    ],
    "version": "2.1.0"
}